LICENSE
mystbin/__init__.py
mystbin/client.py
mystbin/errors.py
mystbin/http.py
mystbin/paste.py
mystbin/py.typed
mystbin/types/__init__.py
mystbin/types/responses.py
mystbin/utils.py
mystbin_py-7.1.0.dist-info/METADATA
mystbin_py-7.1.0.dist-info/WHEEL
mystbin_py-7.1.0.dist-info/entry_points.txt
mystbin_py-7.1.0.dist-info/licenses/LICENSE
mystbin_py-7.1.0.dist-info/RECORD
