Metadata-Version: 2.1
Name: mystbin-py
Version: 7.1.0
Summary: A small simple wrapper around the mystb.in API.
Keywords: mystbin,paste
Author-Email: =?utf-8?q?Alex_N=C3=B8rgaard?= <umbra@abstractumbra.dev>
License: Copyright 2020-Present PythonistaGuild
Classifier: License :: OSI Approved :: MIT License
Classifier: Intended Audience :: Developers
Classifier: Natural Language :: English
Classifier: Operating System :: OS Independent
Classifier: Programming Language :: Python :: 3.8
Classifier: Programming Language :: Python :: 3.9
Classifier: Programming Language :: Python :: 3.10
Classifier: Programming Language :: Python :: 3.11
Classifier: Programming Language :: Python :: 3.12
Classifier: Topic :: Internet
Classifier: Typing :: Typed
Project-URL: Issue Tracker, https://github.com/PythonistaGuild/mystbin.py/issues
Project-URL: homepage, https://github.com/PythonistaGuild/mystbin.py
Project-URL: repository, https://github.com/PythonistaGuild/mystbin.py
Requires-Python: <4.0,>=3.8
Requires-Dist: aiohttp<4.0,>=3.8
Requires-Dist: aiohttp[speedups]<4.0,>=3.8; extra == "speed"
